callfire/__init__.py
callfire/client.py
callfire_api_client_python-0.0.9.dist-info/LICENSE
callfire_api_client_python-0.0.9.dist-info/METADATA
callfire_api_client_python-0.0.9.dist-info/WHEEL
callfire_api_client_python-0.0.9.dist-info/top_level.txt
callfire_api_client_python-0.0.9.dist-info/RECORD
