Metadata-Version: 2.1
Name: callfire-api-client-python
Version: 0.0.9
Summary: CallFire API v2 Python client. Connect voice and text services to your application.
Home-page: https://github.com/CallFire/callfire-api-client-python
Author: Vladimir Mikhailov
Author-email: vmikhailov@callfire.com
License: MIT License
Keywords: CallFire API v2 Python SDK messaging sms mms dialing calls texts
Platform: UNKNOWN
Classifier: Development Status :: 4 - Beta
Classifier: Topic :: Software Development :: Libraries :: Python Modules
Classifier: License :: OSI Approved :: MIT License
Classifier: Operating System :: OS Independent
Classifier: Programming Language :: Python :: 2.7
Classifier: Programming Language :: Python :: 3.6
Requires-Dist: bravado
